jungrad/__init__.py
jungrad/_version.py
jungrad/autograd.py
jungrad/backend.py
jungrad/exceptions.py
jungrad/functional.py
jungrad/graphviz.py
jungrad/hooks.py
jungrad/logging.py
jungrad/losses.py
jungrad/ops.py
jungrad/profiler.py
jungrad/tensor.py
jungrad/types.py
jungrad/utils.py
jungrad/nn/__init__.py
jungrad/nn/init.py
jungrad/nn/layers.py
jungrad/nn/module.py
jungrad/nn/utils.py
jungrad/optim/__init__.py
jungrad/optim/adam.py
jungrad/optim/clip.py
jungrad/optim/rmsprop.py
jungrad/optim/sgd.py
jungrad/sched/__init__.py
jungrad/sched/cosine.py
jungrad/sched/onecycle.py
jungrad/sched/step.py
jungrad/testing/__init__.py
jungrad/testing/gradcheck.py
jungrad-0.2.0.dist-info/licenses/LICENSE
jungrad-0.2.0.dist-info/METADATA
jungrad-0.2.0.dist-info/WHEEL
jungrad-0.2.0.dist-info/top_level.txt
jungrad-0.2.0.dist-info/RECORD
