Metadata-Version: 2.4
Name: JunGrad
Version: 0.2.0
Summary: A robust N-D autograd library with comprehensive ops, NN layers, and optimizers
Home-page: https://github.com/junkim100/JunGrad
Author: JunGrad Contributors
License: MIT License
Project-URL: Homepage, https://github.com/junkim100/JunGrad
Project-URL: Documentation, https://github.com/junkim100/JunGrad#readme
Project-URL: Issues, https://github.com/junkim100/JunGrad/issues
Project-URL: Source, https://github.com/junkim100/JunGrad
Keywords: autograd,numpy,deep-learning,machine-learning
Classifier: Development Status :: 3 - Alpha
Classifier: Intended Audience :: Developers
Classifier: Intended Audience :: Science/Research
Classifier: License :: OSI Approved :: MIT License
Classifier: Programming Language :: Python :: 3
Classifier: Programming Language :: Python :: 3.10
Classifier: Programming Language :: Python :: 3.11
Classifier: Programming Language :: Python :: 3.12
Classifier: Topic :: Scientific/Engineering :: Artificial Intelligence
Requires-Python: >=3.10
License-File: LICENSE
Requires-Dist: numpy>=1.24.0
Provides-Extra: dev
Requires-Dist: black>=24.0.0; extra == "dev"
Requires-Dist: ruff>=0.1.0; extra == "dev"
Requires-Dist: mypy>=1.0.0; extra == "dev"
Requires-Dist: pytest>=7.0.0; extra == "dev"
Requires-Dist: pytest-cov>=4.0.0; extra == "dev"
Requires-Dist: build>=1.2.1; extra == "dev"
Requires-Dist: twine>=4.0.2; extra == "dev"
Provides-Extra: sparse
Requires-Dist: scipy>=1.10.0; extra == "sparse"
Provides-Extra: viz
Requires-Dist: graphviz>=0.20.0; extra == "viz"
Provides-Extra: tutorial
Requires-Dist: datasets>=4.4.0; extra == "tutorial"
Requires-Dist: matplotlib>=3.7.0; extra == "tutorial"
Requires-Dist: scikit-learn>=1.2.0; extra == "tutorial"
Requires-Dist: ipykernel>=6.0.0; extra == "tutorial"
Dynamic: home-page
Dynamic: license-file
Dynamic: requires-python
